{
  "$schema": "./node_modules/@openapitools/openapi-generator-cli/config.schema.json",
  "generator-cli": {
    "version": "5.3.0",
    "generators": {
      "javascript-search": {
        "generatorName": "typescript-node",
        "templateDir": "#{cwd}/templates/javascript/",
        "config": "#{cwd}/openapitools.json",
        "apiPackage": "src",
        "output": "#{cwd}/clients/algoliasearch-client-javascript/client-search",
        "glob": "specs/search/spec.yml",
        "gitHost": "algolia",
        "gitUserId": "algolia",
        "gitRepoId": "algoliasearch-client-javascript",
        "additionalProperties": {
          "modelPropertyNaming": "original",
          "supportsES6": true,
          "npmName": "@algolia/client-search",
          "packageName": "@algolia/client-search",
          "npmVersion": "5.0.0"
        }
      },
      "javascript-recommend": {
        "generatorName": "typescript-node",
        "templateDir": "#{cwd}/templates/javascript/",
        "config": "#{cwd}/openapitools.json",
        "apiPackage": "src",
        "output": "#{cwd}/clients/algoliasearch-client-javascript/recommend",
        "glob": "specs/recommend/spec.yml",
        "gitHost": "algolia",
        "gitUserId": "algolia",
        "gitRepoId": "algoliasearch-client-javascript",
        "reservedWordsMappings": "queryParameters=queryParameters",
        "additionalProperties": {
          "modelPropertyNaming": "original",
          "supportsES6": true,
          "npmName": "@algolia/recommend",
          "packageName": "@algolia/recommend",
          "npmVersion": "5.0.0"
        }
      },
      "javascript-personalization": {
        "generatorName": "typescript-node",
        "templateDir": "#{cwd}/templates/javascript/",
        "config": "#{cwd}/openapitools.json",
        "apiPackage": "src",
        "output": "#{cwd}/clients/algoliasearch-client-javascript/client-personalization",
        "glob": "specs/personalization/spec.yml",
        "gitHost": "algolia",
        "gitUserId": "algolia",
        "gitRepoId": "algoliasearch-client-javascript",
        "additionalProperties": {
          "modelPropertyNaming": "original",
          "supportsES6": true,
          "npmName": "@algolia/client-personalization",
          "packageName": "@algolia/client-personalization",
          "npmVersion": "5.0.0",
          "isPersonalizationHost": false
        }
      },
      "java-search": {
        "generatorName": "java",
        "templateDir": "#{cwd}/templates/java/",
        "config": "#{cwd}/openapitools.json",
        "output": "#{cwd}/clients/algoliasearch-client-java-2",
        "artifactId": "algoliasearch-client-java-2",
        "groupId": "com.algolia",
        "apiPackage": "com.algolia.search",
        "invokerPackage": "com.algolia",
        "modelPackage": "com.algolia.model",
        "library": "okhttp-gson",
        "glob": "specs/search/spec.yml",
        "gitHost": "algolia",
        "gitUserId": "algolia",
        "gitRepoId": "algoliasearch-client-java-2",
        "additionalProperties": {
          "sourceFolder": "algoliasearch-core",
          "java8": true,
          "dateLibrary": "java8"
        }
      }
    }
  }
}
